{
  "chain_type": "build",
  "target": "ApprovalPanel",
  "steps": [
    {"name": "teach", "status": "completed", "conditional": true, "trigger": "PRODUCT.md missing"},
    {"name": "explore", "status": "skipped", "conditional": true, "trigger": "DESIGN.md missing", "reason": "项目已有 Catppuccin Mocha 主题，所有组件遵循统一视觉系统"},
    {"name": "shape", "status": "completed"},
    {"name": "craft", "status": "completed", "notes": "生产构建通过。风险检测扩展、prefers-reduced-motion、focus-visible、触摸目标、响应式、滚动条、ARIA、active 反馈"},
    {"name": "critique", "status": "completed", "notes": "质量门通过 ✓ — 31/40 (≥26), P0=0", "score": "31/40", "p0_count": 0, "p1_count": 2},
    {"name": "refine", "status": "completed", "notes": "质量门通过，refine 循环跳过"},
    {"name": "audit", "status": "completed", "notes": "质量门通过 ✓ — 17/20 (≥14), P0=0, P1=0", "score": "17/20", "p0_count": 0, "p1_count": 0},
    {"name": "polish", "status": "completed", "notes": "4 项修复：1) 对比度 #6c7086→#a6adc8 (WCAG AA)；2) 触摸目标 36px→44px (WCAG 2.5.5)；3) 响应式风险徽章左对齐；4) 可见键盘快捷键指示器 <kbd>。生产构建通过。"}
  ],
  "current_step": 8,
  "gate_history": [
    {"step": "critique", "score": 31, "threshold": 26, "p0_count": 0, "passed": true},
    {"step": "audit", "score": 17, "threshold": 14, "p0_count": 0, "passed": true}
  ],
  "loop_count": 0,
  "status": "completed"
}
